regress-2025.10.1.dist-info/METADATA
regress-2025.10.1.dist-info/WHEEL
regress-2025.10.1.dist-info/licenses/LICENSE
regress/__init__.py
regress/__init__.pyi
regress/py.typed
regress/regress.cpython-314t-aarch64-linux-gnu.so
regress-2025.10.1.dist-info/RECORD
