Metadata-Version: 2.4
Name: regress
Version: 2025.10.1
Classifier: Development Status :: 4 - Beta
Classifier: Intended Audience :: Developers
Classifier: License :: OSI Approved :: MIT License
Classifier: Operating System :: OS Independent
Classifier: Programming Language :: Rust
Classifier: Programming Language :: Python :: 3.10
Classifier: Programming Language :: Python :: 3.11
Classifier: Programming Language :: Python :: 3.12
Classifier: Programming Language :: Python :: 3.13
Classifier: Programming Language :: Python :: 3.14
Classifier: Programming Language :: Python :: 3
Classifier: Programming Language :: Python :: Implementation :: CPython
Classifier: Programming Language :: Python :: Implementation :: PyPy
License-File: LICENSE
Summary: Python bindings to Rust's regress ECMA regular expressions library
Keywords: regex,rust,javascript,ecmascript,regular expressions
Author-email: Julian Berman <Julian+regress@GrayVines.com>
Requires-Python: >=3.10
Project-URL: Homepage, https://github.com/crate-py/regress
Project-URL: Issues, https://github.com/crate-py/regress/issues
Project-URL: Funding, https://github.com/sponsors/Julian
Project-URL: Source, https://github.com/crate-py/regress
Project-URL: Upstream, https://github.com/ridiculousfish/regress
